sqlalchemy_diff-1.1.1.dist-info/METADATA
sqlalchemy_diff-1.1.1.dist-info/WHEEL
sqlalchemy_diff-1.1.1.dist-info/entry_points.txt
sqlalchemy_diff-1.1.1.dist-info/licenses/LICENSE
sqlalchemydiff/__init__.py
sqlalchemydiff/comparer.py
sqlalchemydiff/connection.py
sqlalchemydiff/inspection/__init__.py
sqlalchemydiff/inspection/base.py
sqlalchemydiff/inspection/compat.py
sqlalchemydiff/inspection/exceptions.py
sqlalchemydiff/inspection/ignore.py
sqlalchemydiff/inspection/inspectors.py
sqlalchemydiff/inspection/mixins.py
sqlalchemy_diff-1.1.1.dist-info/RECORD
