Metadata-Version: 2.4
Name: sqlalchemy-diff
Version: 1.1.1
Summary: A tool for comparing database schemas using SQLAlchemy
Keywords: sqlalchemy,diff,compare
Author-Email: Fabrizio Romano <gianchub@gmail.com>, Mark McArdle <m.mc4rdle@gmail.com>
Maintainer-Email: Fabrizio Romano <gianchub@gmail.com>, Mark McArdle <m.mc4rdle@gmail.com>
License-File: LICENSE
Classifier: Programming Language :: Python :: 3
Classifier: Programming Language :: Python :: 3.10
Classifier: Programming Language :: Python :: 3.11
Classifier: Programming Language :: Python :: 3.12
Classifier: Programming Language :: Python :: 3.13
Classifier: Programming Language :: Python :: 3.14
Classifier: License :: OSI Approved :: Apache Software License
Classifier: Intended Audience :: Developers
Classifier: Topic :: Software Development :: Libraries
Classifier: Topic :: Database
Classifier: Operating System :: OS Independent
Project-URL: Homepage, https://github.com/gianchub/sqlalchemy-diff
Project-URL: Issues, https://github.com/gianchub/sqlalchemy-diff/issues
Project-URL: License, https://github.com/gianchub/sqlalchemy-diff/blob/main/LICENSE
Requires-Python: >=3.10
Requires-Dist: sqlalchemy<3,>=1.4
Provides-Extra: dev
Requires-Dist: jupyterlab; extra == "dev"
Requires-Dist: pdbpp; extra == "dev"
Requires-Dist: rich; extra == "dev"
Provides-Extra: lint
Requires-Dist: ruff~=0.14.1; extra == "lint"
Requires-Dist: ty; extra == "lint"
Provides-Extra: test
Requires-Dist: pytest~=9.0.1; extra == "test"
Requires-Dist: pytest-cov~=7.0.0; extra == "test"
Requires-Dist: psycopg2-binary; extra == "test"
Requires-Dist: pytest-xdist>=3.8.0; extra == "test"
Provides-Extra: all
Requires-Dist: sqlalchemy-diff[dev,lint,test]; extra == "all"
